setup.py
test/test_tweethandler.py
tweethandler/__init__.py
tweethandler/setuputil.py
tweethandler/tweethandler.py
tweethandler.egg-info/PKG-INFO
tweethandler.egg-info/SOURCES.txt
tweethandler.egg-info/dependency_links.txt
tweethandler.egg-info/entry_points.txt
tweethandler.egg-info/not-zip-safe
tweethandler.egg-info/requires.txt
tweethandler.egg-info/top_level.txt