Metadata-Version: 1.0
Name: tweethandler
Version: 0.2.0
Summary: logging handler for twitter
Home-page: http://github.com/yssk22/tweethandler
Author: Yohei Sasaki
Author-email: UNKNOWN
License: MIT
Keywords: twitter logging
Platform: UNKNOWN
